bconv/__init__.py
bconv/doc/__init__.py
bconv/doc/document.py
bconv/fmt/__init__.py
bconv/fmt/_export.py
bconv/fmt/_load.py
bconv/fmt/bioc.py
bconv/fmt/brat.py
bconv/fmt/conll.py
bconv/fmt/csv_.py
bconv/fmt/europepmc.py
bconv/fmt/pubanno.py
bconv/fmt/pubmed.py
bconv/fmt/pubtator.py
bconv/fmt/txt.py
bconv/nlp/__init__.py
bconv/nlp/tokenize.py
bconv/util/__init__.py
bconv/util/iterate.py
bconv/util/misc.py
bconv/util/stream.py
bconv-1.2.1.dist-info/LICENSE
bconv-1.2.1.dist-info/METADATA
bconv-1.2.1.dist-info/WHEEL
bconv-1.2.1.dist-info/RECORD
