Metadata-Version: 2.1
Name: bconv
Version: 1.2.1
Summary: Convert between BioNLP formats
Home-page: https://github.com/lfurrer/bconv
License: MIT
Author: Lenz Furrer
Author-email: lenz.furrer@gmail.com
Requires-Python: >=3.7,<4.0
Classifier: License :: OSI Approved :: MIT License
Classifier: Programming Language :: Python :: 3
Classifier: Programming Language :: Python :: 3.7
Classifier: Programming Language :: Python :: 3.8
Classifier: Programming Language :: Python :: 3.9
Classifier: Programming Language :: Python :: 3.10
Classifier: Programming Language :: Python :: 3.11
Requires-Dist: lxml (>=4.3,<5.0)
Requires-Dist: nltk (>=3.4,<4.0)
Project-URL: Documentation, https://github.com/lfurrer/bconv/wiki
Project-URL: Repository, https://github.com/lfurrer/bconv
